mgnifyextract/__init__.py
mgnifyextract/__main__.py
mgnifyextract/analyses.py
mgnifyextract/downloads.py
mgnifyextract/dwc.py
mgnifyextract/runs.py
mgnifyextract/samples.py
mgnifyextract/studies.py
mgnifyextract/util.py
mgnifyextract-0.0.2.dist-info/METADATA
mgnifyextract-0.0.2.dist-info/WHEEL
mgnifyextract-0.0.2.dist-info/top_level.txt
mgnifyextract-0.0.2.dist-info/RECORD
