Metadata-Version: 2.1
Name: mgnifyextract
Version: 0.0.2
Summary: This library extracts Darwin Core datasets from MGnify
Home-page: https://github.com/iobis/mgnify-extract
Author: Pieter Provoost
Author-email: pieterprovoost@gmail.com
License: MIT
Project-URL: Bug Tracker, https://github.com/iobis/mgnify-extract/issues
Project-URL: repository, https://github.com/iobis/mgnify-extract
Requires-Dist: pysam (==0.20.0)
Requires-Dist: pandas (==1.5.0)
Requires-Dist: biopython (==1.80)
Requires-Dist: pdoc (==12.3.1)
Requires-Dist: requests (==2.28.2)
